MANIFEST.in
README.md
setup.py
ecc/Key.py
ecc/Rabbit.py
ecc/SecurityViolationException.py
ecc/__init__.py
ecc/curves.py
ecc/eccrypt.py
ecc/ecdsa.py
ecc/elliptic.py
ecc/encoding.py
ecc/performance.py
ecc/primes.py
ecc/shacrypt.py
ecc.egg-info/PKG-INFO
ecc.egg-info/SOURCES.txt
ecc.egg-info/dependency_links.txt
ecc.egg-info/top_level.txt